nextrec/__init__.py
nextrec/__version__.py
nextrec/cli.py
nextrec/basic/__init__.py
nextrec/basic/activation.py
nextrec/basic/asserts.py
nextrec/basic/callback.py
nextrec/basic/features.py
nextrec/basic/heads.py
nextrec/basic/layers.py
nextrec/basic/loggers.py
nextrec/basic/metrics.py
nextrec/basic/model.py
nextrec/basic/session.py
nextrec/basic/summary.py
nextrec/data/__init__.py
nextrec/data/batch_utils.py
nextrec/data/data_processing.py
nextrec/data/data_utils.py
nextrec/data/dataloader.py
nextrec/data/preprocessor.py
nextrec/loss/__init__.py
nextrec/loss/grad_norm.py
nextrec/loss/listwise.py
nextrec/loss/pairwise.py
nextrec/loss/pointwise.py
nextrec/models/generative/__init__.py
nextrec/models/generative/tiger.py
nextrec/models/multi_task/[pre]aitm.py
nextrec/models/multi_task/[pre]snr_trans.py
nextrec/models/multi_task/[pre]star.py
nextrec/models/multi_task/__init__.py
nextrec/models/multi_task/apg.py
nextrec/models/multi_task/cross_stitch.py
nextrec/models/multi_task/escm.py
nextrec/models/multi_task/esmm.py
nextrec/models/multi_task/hmoe.py
nextrec/models/multi_task/mmoe.py
nextrec/models/multi_task/pepnet.py
nextrec/models/multi_task/ple.py
nextrec/models/multi_task/poso.py
nextrec/models/multi_task/share_bottom.py
nextrec/models/ranking/__init__.py
nextrec/models/ranking/afm.py
nextrec/models/ranking/autoint.py
nextrec/models/ranking/dcn.py
nextrec/models/ranking/dcn_v2.py
nextrec/models/ranking/deepfm.py
nextrec/models/ranking/dien.py
nextrec/models/ranking/din.py
nextrec/models/ranking/eulernet.py
nextrec/models/ranking/ffm.py
nextrec/models/ranking/fibinet.py
nextrec/models/ranking/fm.py
nextrec/models/ranking/lr.py
nextrec/models/ranking/masknet.py
nextrec/models/ranking/pnn.py
nextrec/models/ranking/widedeep.py
nextrec/models/ranking/xdeepfm.py
nextrec/models/representation/__init__.py
nextrec/models/representation/autorec.py
nextrec/models/representation/bpr.py
nextrec/models/representation/cl4srec.py
nextrec/models/representation/lightgcn.py
nextrec-0.4.33.dist-info/METADATA
nextrec-0.4.33.dist-info/WHEEL
nextrec-0.4.33.dist-info/entry_points.txt
nextrec-0.4.33.dist-info/licenses/LICENSE
nextrec-0.4.33.dist-info/RECORD
