Metadata-Version: 2.4
Name: nextrec
Version: 0.4.33
Summary: A comprehensive recommendation library with match, ranking, and multi-task learning models
Project-URL: Homepage, https://github.com/zerolovesea/NextRec
Project-URL: Repository, https://github.com/zerolovesea/NextRec
Project-URL: Documentation, https://github.com/zerolovesea/NextRec/blob/main/README.md
Project-URL: Issues, https://github.com/zerolovesea/NextRec/issues
Author: Yang Zhou
Author-email: zyaztec@gmail.com
License-File: LICENSE
Keywords: ctr,deep-learning,match,pytorch,ranking,recommendation
Classifier: Development Status :: 3 - Alpha
Classifier: Intended Audience :: Developers
Classifier: Intended Audience :: Science/Research
Classifier: License :: OSI Approved :: Apache Software License
Classifier: Programming Language :: Python :: 3
Classifier: Programming Language :: Python :: 3.10
Classifier: Programming Language :: Python :: 3.11
Classifier: Programming Language :: Python :: 3.12
Classifier: Topic :: Scientific/Engineering :: Artificial Intelligence
Requires-Python: >=3.10
Requires-Dist: numpy<2.0,>=1.21; sys_platform == 'linux' and python_version < '3.12'
Requires-Dist: numpy<3.0,>=1.26; sys_platform == 'linux' and python_version >= '3.12'
Requires-Dist: numpy>=1.23.0; sys_platform == 'win32'
Requires-Dist: numpy>=1.24.0; sys_platform == 'darwin'
Requires-Dist: pandas<2.0,>=1.5; sys_platform == 'linux' and python_version < '3.12'
Requires-Dist: pandas<2.3.0,>=2.1.0; sys_platform == 'win32'
Requires-Dist: pandas>=2.0.0; sys_platform == 'darwin'
Requires-Dist: pandas>=2.1.0; sys_platform == 'linux' and python_version >= '3.12'
Requires-Dist: pyarrow<13.0.0,>=10.0.0; sys_platform == 'linux' and python_version < '3.12'
Requires-Dist: pyarrow<15.0.0,>=12.0.0; sys_platform == 'win32'
Requires-Dist: pyarrow>=12.0.0; sys_platform == 'darwin'
Requires-Dist: pyarrow>=16.0.0; sys_platform == 'linux' and python_version >= '3.12'
Requires-Dist: pyyaml>=6.0
Requires-Dist: rich>=13.7.0
Requires-Dist: scikit-learn<2.0,>=1.2; sys_platform == 'linux' and python_version < '3.12'
Requires-Dist: scikit-learn>=1.3.0; sys_platform == 'darwin'
Requires-Dist: scikit-learn>=1.3.0; sys_platform == 'linux' and python_version >= '3.12'
Requires-Dist: scikit-learn>=1.3.0; sys_platform == 'win32'
Requires-Dist: scipy<1.12,>=1.8; sys_platform == 'linux' and python_version < '3.12'
Requires-Dist: scipy>=1.10.0; sys_platform == 'darwin'
Requires-Dist: scipy>=1.10.0; sys_platform == 'win32'
Requires-Dist: scipy>=1.11.0; sys_platform == 'linux' and python_version >= '3.12'
Requires-Dist: swanlab>=0.7.2
Requires-Dist: torch>=2.0.0
Requires-Dist: torchvision>=0.15.0
Requires-Dist: transformers>=4.38.0
Requires-Dist: wandb>=0.23.1
Provides-Extra: dev
Requires-Dist: jupyter>=1.0.0; extra == 'dev'
Requires-Dist: matplotlib>=3.7.0; extra == 'dev'
Requires-Dist: pytest-cov>=4.1.0; extra == 'dev'
Requires-Dist: pytest-html>=3.2.0; extra == 'dev'
Requires-Dist: pytest-mock>=3.11.0; extra == 'dev'
Requires-Dist: pytest-timeout>=2.1.0; extra == 'dev'
Requires-Dist: pytest-xdist>=3.3.0; extra == 'dev'
Requires-Dist: pytest>=7.4.0; extra == 'dev'
Requires-Dist: seaborn>=0.12.0; extra == 'dev'
